odoo10_addon_delivery_carrier_b2c-10.0.0.1.0-py2.7-nspkg.pth
odoo10_addon_delivery_carrier_b2c-10.0.0.1.0.dist-info/top_level.txt
odoo10_addon_delivery_carrier_b2c-10.0.0.1.0.dist-info/WHEEL
odoo10_addon_delivery_carrier_b2c-10.0.0.1.0.dist-info/RECORD
odoo10_addon_delivery_carrier_b2c-10.0.0.1.0.dist-info/metadata.json
odoo10_addon_delivery_carrier_b2c-10.0.0.1.0.dist-info/DESCRIPTION.rst
odoo10_addon_delivery_carrier_b2c-10.0.0.1.0.dist-info/METADATA
odoo10_addon_delivery_carrier_b2c-10.0.0.1.0.dist-info/namespace_packages.txt
odoo/addons/delivery_carrier_b2c/__manifest__.py
odoo/addons/delivery_carrier_b2c/partner.py
odoo/addons/delivery_carrier_b2c/__init__.py
odoo/addons/delivery_carrier_b2c/README.rst
odoo/addons/delivery_carrier_b2c/partner_view.xml
odoo/addons/delivery_carrier_b2c/i18n/delivery_carrier_b2c.pot
odoo/addons/delivery_carrier_b2c/i18n/sl.po
odoo/addons/delivery_carrier_b2c/i18n/de.po
odoo/addons/delivery_carrier_b2c/i18n/pt_BR.po
